multipyline/__init__.py
multipyline/multipyline.py
multipyline/multipyline_format.py
multipyline/multipyline_inner.py
multipyline/py.typed
multipyline-0.1.0.dist-info/METADATA
multipyline-0.1.0.dist-info/WHEEL
multipyline-0.1.0.dist-info/licenses/LICENSE
multipyline-0.1.0.dist-info/RECORD
