Metadata-Version: 2.4
Name: multipyline
Version: 0.1.0
Summary: A Python package for easier multiline string formatting
Author-email: Mojmír Majer <mojmir.majer@gmail.com>
License-File: LICENSE
Requires-Python: >=3.12
